<?xml version="1.0" encoding="UTF-8" standalone="no"?>
<geonames>
<totalResultsCount>1131</totalResultsCount>
<code>
<postalcode>55082</postalcode>
<name>Stillwater</name>
<countryCode>US</countryCode>
<lat>45.06142</lat>
<lng>-92.84736</lng>
<adminCode1>MN</adminCode1>
<adminName1>Minnesota</adminName1>
<adminCode2>163</adminCode2>
<adminName2>Washington</adminName2>
<adminCode3/>
<adminName3/>
</code>
<code>
<postalcode>55044</postalcode>
<name>Lakeville</name>
<countryCode>US</countryCode>
<lat>44.67486</lat>
<lng>-93.2578</lng>
<adminCode1>MN</adminCode1>
<adminName1>Minnesota</adminName1>
<adminCode2>037</adminCode2>
<adminName2>Dakota</adminName2>
<adminCode3/>
<adminName3/>
</code>
<code>
<postalcode>55303</postalcode>
<name>Anoka</name>
<countryCode>US</countryCode>
<lat>45.28248</lat>
<lng>-93.41857</lng>
<adminCode1>MN</adminCode1>
<adminName1>Minnesota</adminName1>
<adminCode2>003</adminCode2>
<adminName2>Anoka</adminName2>
<adminCode3/>
<adminName3/>
</code>
<code>
<postalcode>55337</postalcode>
<name>Burnsville</name>
<countryCode>US</countryCode>
<lat>44.76086</lat>
<lng>-93.27528</lng>
<adminCode1>MN</adminCode1>
<adminName1>Minnesota</adminName1>
<adminCode2>037</adminCode2>
<adminName2>Dakota</adminName2>
<adminCode3/>
<adminName3/>
</code>
<code>
<postalcode>55368</postalcode>
<name>Norwood</name>
<countryCode>US</countryCode>
<lat>44.76679</lat>
<lng>-93.93007</lng>
<adminCode1>MN</adminCode1>
<adminName1>Minnesota</adminName1>
<adminCode2>019</adminCode2>
<adminName2>Carver</adminName2>
<adminCode3/>
<adminName3/>
</code>
<code>
<postalcode>55379</postalcode>
<name>Shakopee</name>
<countryCode>US</countryCode>
<lat>44.7793</lat>
<lng>-93.51975</lng>
<adminCode1>MN</adminCode1>
<adminName1>Minnesota</adminName1>
<adminCode2>139</adminCode2>
<adminName2>Scott</adminName2>
<adminCode3/>
<adminName3/>
</code>
<code>
<postalcode>55386</postalcode>
<name>Victoria</name>
<countryCode>US</countryCode>
<lat>44.85822</lat>
<lng>-93.65609</lng>
<adminCode1>MN</adminCode1>
<adminName1>Minnesota</adminName1>
<adminCode2>019</adminCode2>
<adminName2>Carver</adminName2>
<adminCode3/>
<adminName3/>
</code>
<code>
<postalcode>55401</postalcode>
<name>Minneapolis</name>
<countryCode>US</countryCode>
<lat>44.98347</lat>
<lng>-93.26825</lng>
<adminCode1>MN</adminCode1>
<adminName1>Minnesota</adminName1>
<adminCode2>053</adminCode2>
<adminName2>Hennepin</adminName2>
<adminCode3/>
<adminName3/>
</code>
<code>
<postalcode>55402</postalcode>
<name>Minneapolis</name>
<countryCode>US</countryCode>
<lat>44.97618</lat>
<lng>-93.27587</lng>
<adminCode1>MN</adminCode1>
<adminName1>Minnesota</adminName1>
<adminCode2>053</adminCode2>
<adminName2>Hennepin</adminName2>
<adminCode3/>
<adminName3/>
</code>
<code>
<postalcode>55403</postalcode>
<name>Minneapolis</name>
<countryCode>US</countryCode>
<lat>44.96734</lat>
<lng>-93.28284</lng>
<adminCode1>MN</adminCode1>
<adminName1>Minnesota</adminName1>
<adminCode2>053</adminCode2>
<adminName2>Hennepin</adminName2>
<adminCode3/>
<adminName3/>
</code>
<code>
<postalcode>55414</postalcode>
<name>Minneapolis</name>
<countryCode>US</countryCode>
<lat>44.97791</lat>
<lng>-93.2199</lng>
<adminCode1>MN</adminCode1>
<adminName1>Minnesota</adminName1>
<adminCode2>053</adminCode2>
<adminName2>Hennepin</adminName2>
<adminCode3/>
<adminName3/>
</code>
<code>
<postalcode>55901</postalcode>
<name>Rochester</name>
<countryCode>US</countryCode>
<lat>44.04957</lat>
<lng>-92.48962</lng>
<adminCode1>MN</adminCode1>
<adminName1>Minnesota</adminName1>
<adminCode2>109</adminCode2>
<adminName2>Olmsted</adminName2>
<adminCode3/>
<adminName3/>
</code>
<code>
<postalcode>55902</postalcode>
<name>Rochester</name>
<countryCode>US</countryCode>
<lat>44.00322</lat>
<lng>-92.48352</lng>
<adminCode1>MN</adminCode1>
<adminName1>Minnesota</adminName1>
<adminCode2>109</adminCode2>
<adminName2>Olmsted</adminName2>
<adminCode3/>
<adminName3/>
</code>
<code>
<postalcode>55904</postalcode>
<name>Rochester</name>
<countryCode>US</countryCode>
<lat>44.01054</lat>
<lng>-92.39728</lng>
<adminCode1>MN</adminCode1>
<adminName1>Minnesota</adminName1>
<adminCode2>109</adminCode2>
<adminName2>Olmsted</adminName2>
<adminCode3/>
<adminName3/>
</code>
<code>
<postalcode>56308</postalcode>
<name>Alexandria</name>
<countryCode>US</countryCode>
<lat>45.88175</lat>
<lng>-95.38199</lng>
<adminCode1>MN</adminCode1>
<adminName1>Minnesota</adminName1>
<adminCode2>041</adminCode2>
<adminName2>Douglas</adminName2>
<adminCode3/>
<adminName3/>
</code>
<code>
<postalcode>56560</postalcode>
<name>Moorhead</name>
<countryCode>US</countryCode>
<lat>46.86775</lat>
<lng>-96.7572</lng>
<adminCode1>MN</adminCode1>
<adminName1>Minnesota</adminName1>
<adminCode2>027</adminCode2>
<adminName2>Clay</adminName2>
<adminCode3/>
<adminName3/>
</code>
<code>
<postalcode>56601</postalcode>
<name>Bemidji</name>
<countryCode>US</countryCode>
<lat>47.57196</lat>
<lng>-94.80127</lng>
<adminCode1>MN</adminCode1>
<adminName1>Minnesota</adminName1>
<adminCode2>007</adminCode2>
<adminName2>Beltrami</adminName2>
<adminCode3/>
<adminName3/>
</code>
<code>
<postalcode>55330</postalcode>
<name>Elk River</name>
<countryCode>US</countryCode>
<lat>45.3136</lat>
<lng>-93.5814</lng>
<adminCode1>MN</adminCode1>
<adminName1>Minnesota</adminName1>
<adminCode2>141</adminCode2>
<adminName2>Sherburne</adminName2>
<adminCode3/>
<adminName3/>
</code>
<code>
<postalcode>55344</postalcode>
<name>Eden Prairie</name>
<countryCode>US</countryCode>
<lat>44.85743</lat>
<lng>-93.43757</lng>
<adminCode1>MN</adminCode1>
<adminName1>Minnesota</adminName1>
<adminCode2>053</adminCode2>
<adminName2>Hennepin</adminName2>
<adminCode3/>
<adminName3/>
</code>
<code>
<postalcode>55802</postalcode>
<name>Duluth</name>
<countryCode>US</countryCode>
<lat>46.76848</lat>
<lng>-92.0865</lng>
<adminCode1>MN</adminCode1>
<adminName1>Minnesota</adminName1>
<adminCode2>137</adminCode2>
<adminName2>St. Louis</adminName2>
<adminCode3/>
<adminName3/>
</code>
<code>
<postalcode>55001</postalcode>
<name>Afton</name>
<countryCode>US</countryCode>
<lat>44.86965</lat>
<lng>-92.82336</lng>
<adminCode1>MN</adminCode1>
<adminName1>Minnesota</adminName1>
<adminCode2>163</adminCode2>
<adminName2>Washington</adminName2>
<adminCode3/>
<adminName3/>
</code>
<code>
<postalcode>55003</postalcode>
<name>Bayport</name>
<countryCode>US</countryCode>
<lat>45.0214</lat>
<lng>-92.78438</lng>
<adminCode1>MN</adminCode1>
<adminName1>Minnesota</adminName1>
<adminCode2>163</adminCode2>
<adminName2>Washington</adminName2>
<adminCode3/>
<adminName3/>
</code>
<code>
<postalcode>55005</postalcode>
<name>Bethel</name>
<countryCode>US</countryCode>
<lat>45.38872</lat>
<lng>-93.23154</lng>
<adminCode1>MN</adminCode1>
<adminName1>Minnesota</adminName1>
<adminCode2>003</adminCode2>
<adminName2>Anoka</adminName2>
<adminCode3/>
<adminName3/>
</code>
<code>
<postalcode>55006</postalcode>
<name>Braham</name>
<countryCode>US</countryCode>
<lat>45.71755</lat>
<lng>-93.2037</lng>
<adminCode1>MN</adminCode1>
<adminName1>Minnesota</adminName1>
<adminCode2>059</adminCode2>
<adminName2>Isanti</adminName2>
<adminCode3/>
<adminName3/>
</code>
<code>
<postalcode>55008</postalcode>
<name>Cambridge</name>
<countryCode>US</countryCode>
<lat>45.55759</lat>
<lng>-93.28894</lng>
<adminCode1>MN</adminCode1>
<adminName1>Minnesota</adminName1>
<adminCode2>059</adminCode2>
<adminName2>Isanti</adminName2>
<adminCode3/>
<adminName3/>
</code>
<code>
<postalcode>55009</postalcode>
<name>Cannon Falls</name>
<countryCode>US</countryCode>
<lat>44.49598</lat>
<lng>-92.864</lng>
<adminCode1>MN</adminCode1>
<adminName1>Minnesota</adminName1>
<adminCode2>049</adminCode2>
<adminName2>Goodhue</adminName2>
<adminCode3/>
<adminName3/>
</code>
<code>
<postalcode>55010</postalcode>
<name>Castle Rock</name>
<countryCode>US</countryCode>
<lat>44.54722</lat>
<lng>-93.15312</lng>
<adminCode1>MN</adminCode1>
<adminName1>Minnesota</adminName1>
<adminCode2>037</adminCode2>
<adminName2>Dakota</adminName2>
<adminCode3/>
<adminName3/>
</code>
<code>
<postalcode>55011</postalcode>
<name>Cedar</name>
<countryCode>US</countryCode>
<lat>45.34145</lat>
<lng>-93.23503</lng>
<adminCode1>MN</adminCode1>
<adminName1>Minnesota</adminName1>
<adminCode2>003</adminCode2>
<adminName2>Anoka</adminName2>
<adminCode3/>
<adminName3/>
</code>
<code>
<postalcode>55013</postalcode>
<name>Chisago City</name>
<countryCode>US</countryCode>
<lat>45.36114</lat>
<lng>-92.89213</lng>
<adminCode1>MN</adminCode1>
<adminName1>Minnesota</adminName1>
<adminCode2>025</adminCode2>
<adminName2>Chisago</adminName2>
<adminCode3/>
<adminName3/>
</code>
<code>
<postalcode>55016</postalcode>
<name>Cottage Grove</name>
<countryCode>US</countryCode>
<lat>44.83082</lat>
<lng>-92.93928</lng>
<adminCode1>MN</adminCode1>
<adminName1>Minnesota</adminName1>
<adminCode2>163</adminCode2>
<adminName2>Washington</adminName2>
<adminCode3/>
<adminName3/>
</code>
<code>
<postalcode>55017</postalcode>
<name>Dalbo</name>
<countryCode>US</countryCode>
<lat>45.67874</lat>
<lng>-93.44192</lng>
<adminCode1>MN</adminCode1>
<adminName1>Minnesota</adminName1>
<adminCode2>059</adminCode2>
<adminName2>Isanti</adminName2>
<adminCode3/>
<adminName3/>
</code>
<code>
<postalcode>55018</postalcode>
<name>Dennison</name>
<countryCode>US</countryCode>
<lat>44.42654</lat>
<lng>-92.95536</lng>
<adminCode1>MN</adminCode1>
<adminName1>Minnesota</adminName1>
<adminCode2>049</adminCode2>
<adminName2>Goodhue</adminName2>
<adminCode3/>
<adminName3/>
</code>
<code>
<postalcode>55019</postalcode>
<name>Dundas</name>
<countryCode>US</countryCode>
<lat>44.39554</lat>
<lng>-93.20369</lng>
<adminCode1>MN</adminCode1>
<adminName1>Minnesota</adminName1>
<adminCode2>131</adminCode2>
<adminName2>Rice</adminName2>
<adminCode3/>
<adminName3/>
</code>
<code>
<postalcode>55020</postalcode>
<name>Elko</name>
<countryCode>US</countryCode>
<lat>44.58945</lat>
<lng>-93.38356</lng>
<adminCode1>MN</adminCode1>
<adminName1>Minnesota</adminName1>
<adminCode2>139</adminCode2>
<adminName2>Scott</adminName2>
<adminCode3/>
<adminName3/>
</code>
<code>
<postalcode>55021</postalcode>
<name>Faribault</name>
<countryCode>US</countryCode>
<lat>44.29446</lat>
<lng>-93.28179</lng>
<adminCode1>MN</adminCode1>
<adminName1>Minnesota</adminName1>
<adminCode2>131</adminCode2>
<adminName2>Rice</adminName2>
<adminCode3/>
<adminName3/>
</code>
<code>
<postalcode>55024</postalcode>
<name>Farmington</name>
<countryCode>US</countryCode>
<lat>44.6628</lat>
<lng>-93.15389</lng>
<adminCode1>MN</adminCode1>
<adminName1>Minnesota</adminName1>
<adminCode2>037</adminCode2>
<adminName2>Dakota</adminName2>
<adminCode3/>
<adminName3/>
</code>
<code>
<postalcode>55025</postalcode>
<name>Forest Lake</name>
<countryCode>US</countryCode>
<lat>45.2685</lat>
<lng>-92.97489</lng>
<adminCode1>MN</adminCode1>
<adminName1>Minnesota</adminName1>
<adminCode2>163</adminCode2>
<adminName2>Washington</adminName2>
<adminCode3/>
<adminName3/>
</code>
<code>
<postalcode>55026</postalcode>
<name>Frontenac</name>
<countryCode>US</countryCode>
<lat>44.52004</lat>
<lng>-92.35816</lng>
<adminCode1>MN</adminCode1>
<adminName1>Minnesota</adminName1>
<adminCode2>049</adminCode2>
<adminName2>Goodhue</adminName2>
<adminCode3/>
<adminName3/>
</code>
<code>
<postalcode>55027</postalcode>
<name>Goodhue</name>
<countryCode>US</countryCode>
<lat>44.40218</lat>
<lng>-92.57174</lng>
<adminCode1>MN</adminCode1>
<adminName1>Minnesota</adminName1>
<adminCode2>049</adminCode2>
<adminName2>Goodhue</adminName2>
<adminCode3/>
<adminName3/>
</code>
<code>
<postalcode>55029</postalcode>
<name>Grandy</name>
<countryCode>US</countryCode>
<lat>45.64224</lat>
<lng>-93.20111</lng>
<adminCode1>MN</adminCode1>
<adminName1>Minnesota</adminName1>
<adminCode2>059</adminCode2>
<adminName2>Isanti</adminName2>
<adminCode3/>
<adminName3/>
</code>
<code>
<postalcode>55030</postalcode>
<name>Grasston</name>
<countryCode>US</countryCode>
<lat>45.8566</lat>
<lng>-93.08126</lng>
<adminCode1>MN</adminCode1>
<adminName1>Minnesota</adminName1>
<adminCode2>115</adminCode2>
<adminName2>Pine</adminName2>
<adminCode3/>
<adminName3/>
</code>
<code>
<postalcode>55031</postalcode>
<name>Hampton</name>
<countryCode>US</countryCode>
<lat>44.60285</lat>
<lng>-92.94667</lng>
<adminCode1>MN</adminCode1>
<adminName1>Minnesota</adminName1>
<adminCode2>037</adminCode2>
<adminName2>Dakota</adminName2>
<adminCode3/>
<adminName3/>
</code>
<code>
<postalcode>55032</postalcode>
<name>Harris</name>
<countryCode>US</countryCode>
<lat>45.5962</lat>
<lng>-93.03954</lng>
<adminCode1>MN</adminCode1>
<adminName1>Minnesota</adminName1>
<adminCode2>025</adminCode2>
<adminName2>Chisago</adminName2>
<adminCode3/>
<adminName3/>
</code>
<code>
<postalcode>55033</postalcode>
<name>Hastings</name>
<countryCode>US</countryCode>
<lat>44.7129</lat>
<lng>-92.86373</lng>
<adminCode1>MN</adminCode1>
<adminName1>Minnesota</adminName1>
<adminCode2>037</adminCode2>
<adminName2>Dakota</adminName2>
<adminCode3/>
<adminName3/>
</code>
<code>
<postalcode>55036</postalcode>
<name>Henriette</name>
<countryCode>US</countryCode>
<lat>45.87125</lat>
<lng>-93.11956</lng>
<adminCode1>MN</adminCode1>
<adminName1>Minnesota</adminName1>
<adminCode2>115</adminCode2>
<adminName2>Pine</adminName2>
<adminCode3/>
<adminName3/>
</code>
<code>
<postalcode>55037</postalcode>
<name>Hinckley</name>
<countryCode>US</countryCode>
<lat>46.01888</lat>
<lng>-92.89933</lng>
<adminCode1>MN</adminCode1>
<adminName1>Minnesota</adminName1>
<adminCode2>115</adminCode2>
<adminName2>Pine</adminName2>
<adminCode3/>
<adminName3/>
</code>
<code>
<postalcode>55038</postalcode>
<name>Hugo</name>
<countryCode>US</countryCode>
<lat>45.18237</lat>
<lng>-92.94522</lng>
<adminCode1>MN</adminCode1>
<adminName1>Minnesota</adminName1>
<adminCode2>163</adminCode2>
<adminName2>Washington</adminName2>
<adminCode3/>
<adminName3/>
</code>
<code>
<postalcode>55040</postalcode>
<name>Isanti</name>
<countryCode>US</countryCode>
<lat>45.46821</lat>
<lng>-93.22656</lng>
<adminCode1>MN</adminCode1>
<adminName1>Minnesota</adminName1>
<adminCode2>059</adminCode2>
<adminName2>Isanti</adminName2>
<adminCode3/>
<adminName3/>
</code>
<code>
<postalcode>55042</postalcode>
<name>Lake Elmo</name>
<countryCode>US</countryCode>
<lat>44.99461</lat>
<lng>-92.90565</lng>
<adminCode1>MN</adminCode1>
<adminName1>Minnesota</adminName1>
<adminCode2>163</adminCode2>
<adminName2>Washington</adminName2>
<adminCode3/>
<adminName3/>
</code>
<code>
<postalcode>55043</postalcode>
<name>Lakeland</name>
<countryCode>US</countryCode>
<lat>44.93938</lat>
<lng>-92.77159</lng>
<adminCode1>MN</adminCode1>
<adminName1>Minnesota</adminName1>
<adminCode2>163</adminCode2>
<adminName2>Washington</adminName2>
<adminCode3/>
<adminName3/>
</code>
<code>
<postalcode>55045</postalcode>
<name>Lindstrom</name>
<countryCode>US</countryCode>
<lat>45.38726</lat>
<lng>-92.84208</lng>
<adminCode1>MN</adminCode1>
<adminName1>Minnesota</adminName1>
<adminCode2>025</adminCode2>
<adminName2>Chisago</adminName2>
<adminCode3/>
<adminName3/>
</code>
<code>
<postalcode>55046</postalcode>
<name>Lonsdale</name>
<countryCode>US</countryCode>
<lat>44.4477</lat>
<lng>-93.42516</lng>
<adminCode1>MN</adminCode1>
<adminName1>Minnesota</adminName1>
<adminCode2>131</adminCode2>
<adminName2>Rice</adminName2>
<adminCode3/>
<adminName3/>
</code>
<code>
<postalcode>55049</postalcode>
<name>Medford</name>
<countryCode>US</countryCode>
<lat>44.17415</lat>
<lng>-93.24372</lng>
<adminCode1>MN</adminCode1>
<adminName1>Minnesota</adminName1>
<adminCode2>147</adminCode2>
<adminName2>Steele</adminName2>
<adminCode3/>
<adminName3/>
</code>
<code>
<postalcode>55051</postalcode>
<name>Mora</name>
<countryCode>US</countryCode>
<lat>45.89579</lat>
<lng>-93.29423</lng>
<adminCode1>MN</adminCode1>
<adminName1>Minnesota</adminName1>
<adminCode2>065</adminCode2>
<adminName2>Kanabec</adminName2>
<adminCode3/>
<adminName3/>
</code>
<code>
<postalcode>55052</postalcode>
<name>Morristown</name>
<countryCode>US</countryCode>
<lat>44.23418</lat>
<lng>-93.45251</lng>
<adminCode1>MN</adminCode1>
<adminName1>Minnesota</adminName1>
<adminCode2>131</adminCode2>
<adminName2>Rice</adminName2>
<adminCode3/>
<adminName3/>
</code>
<code>
<postalcode>55053</postalcode>
<name>Nerstrand</name>
<countryCode>US</countryCode>
<lat>44.35377</lat>
<lng>-93.0855</lng>
<adminCode1>MN</adminCode1>
<adminName1>Minnesota</adminName1>
<adminCode2>131</adminCode2>
<adminName2>Rice</adminName2>
<adminCode3/>
<adminName3/>
</code>
<code>
<postalcode>55055</postalcode>
<name>Newport</name>
<countryCode>US</countryCode>
<lat>44.87252</lat>
<lng>-92.9986</lng>
<adminCode1>MN</adminCode1>
<adminName1>Minnesota</adminName1>
<adminCode2>163</adminCode2>
<adminName2>Washington</adminName2>
<adminCode3/>
<adminName3/>
</code>
<code>
<postalcode>55057</postalcode>
<name>Northfield</name>
<countryCode>US</countryCode>
<lat>44.45872</lat>
<lng>-93.16683</lng>
<adminCode1>MN</adminCode1>
<adminName1>Minnesota</adminName1>
<adminCode2>131</adminCode2>
<adminName2>Rice</adminName2>
<adminCode3/>
<adminName3/>
</code>
<code>
<postalcode>55060</postalcode>
<name>Owatonna</name>
<countryCode>US</countryCode>
<lat>44.08048</lat>
<lng>-93.21914</lng>
<adminCode1>MN</adminCode1>
<adminName1>Minnesota</adminName1>
<adminCode2>147</adminCode2>
<adminName2>Steele</adminName2>
<adminCode3/>
<adminName3/>
</code>
<code>
<postalcode>55065</postalcode>
<name>Randolph</name>
<countryCode>US</countryCode>
<lat>44.52739</lat>
<lng>-93.01962</lng>
<adminCode1>MN</adminCode1>
<adminName1>Minnesota</adminName1>
<adminCode2>037</adminCode2>
<adminName2>Dakota</adminName2>
<adminCode3/>
<adminName3/>
</code>
<code>
<postalcode>55066</postalcode>
<name>Red Wing</name>
<countryCode>US</countryCode>
<lat>44.55278</lat>
<lng>-92.54856</lng>
<adminCode1>MN</adminCode1>
<adminName1>Minnesota</adminName1>
<adminCode2>049</adminCode2>
<adminName2>Goodhue</adminName2>
<adminCode3/>
<adminName3/>
</code>
<code>
<postalcode>55068</postalcode>
<name>Rosemount</name>
<countryCode>US</countryCode>
<lat>44.73783</lat>
<lng>-93.06852</lng>
<adminCode1>MN</adminCode1>
<adminName1>Minnesota</adminName1>
<adminCode2>037</adminCode2>
<adminName2>Dakota</adminName2>
<adminCode3/>
<adminName3/>
</code>
<code>
<postalcode>55072</postalcode>
<name>Sandstone</name>
<countryCode>US</countryCode>
<lat>46.13245</lat>
<lng>-92.58896</lng>
<adminCode1>MN</adminCode1>
<adminName1>Minnesota</adminName1>
<adminCode2>115</adminCode2>
<adminName2>Pine</adminName2>
<adminCode3/>
<adminName3/>
</code>
<code>
<postalcode>55073</postalcode>
<name>Scandia</name>
<countryCode>US</countryCode>
<lat>45.26967</lat>
<lng>-92.82916</lng>
<adminCode1>MN</adminCode1>
<adminName1>Minnesota</adminName1>
<adminCode2>163</adminCode2>
<adminName2>Washington</adminName2>
<adminCode3/>
<adminName3/>
</code>
<code>
<postalcode>55074</postalcode>
<name>Shafer</name>
<countryCode>US</countryCode>
<lat>45.35756</lat>
<lng>-92.76089</lng>
<adminCode1>MN</adminCode1>
<adminName1>Minnesota</adminName1>
<adminCode2>025</adminCode2>
<adminName2>Chisago</adminName2>
<adminCode3/>
<adminName3/>
</code>
<code>
<postalcode>55078</postalcode>
<name>Stacy</name>
<countryCode>US</countryCode>
<lat>45.51345</lat>
<lng>-92.89424</lng>
<adminCode1>MN</adminCode1>
<adminName1>Minnesota</adminName1>
<adminCode2>025</adminCode2>
<adminName2>Chisago</adminName2>
<adminCode3/>
<adminName3/>
</code>
<code>
<postalcode>55079</postalcode>
<name>Stacy</name>
<countryCode>US</countryCode>
<lat>45.39751</lat>
<lng>-93.01774</lng>
<adminCode1>MN</adminCode1>
<adminName1>Minnesota</adminName1>
<adminCode2>025</adminCode2>
<adminName2>Chisago</adminName2>
<adminCode3/>
<adminName3/>
</code>
<code>
<postalcode>55080</postalcode>
<name>Stanchfield</name>
<countryCode>US</countryCode>
<lat>45.66751</lat>
<lng>-93.2433</lng>
<adminCode1>MN</adminCode1>
<adminName1>Minnesota</adminName1>
<adminCode2>059</adminCode2>
<adminName2>Isanti</adminName2>
<adminCode3/>
<adminName3/>
</code>
<code>
<postalcode>55083</postalcode>
<name>Stillwater</name>
<countryCode>US</countryCode>
<lat>45.02102</lat>
<lng>-92.98373</lng>
<adminCode1>MN</adminCode1>
<adminName1>Minnesota</adminName1>
<adminCode2>163</adminCode2>
<adminName2>Washington</adminName2>
<adminCode3/>
<adminName3/>
</code>
<code>
<postalcode>55085</postalcode>
<name>Vermillion</name>
<countryCode>US</countryCode>
<lat>44.6748</lat>
<lng>-92.96831</lng>
<adminCode1>MN</adminCode1>
<adminName1>Minnesota</adminName1>
<adminCode2>037</adminCode2>
<adminName2>Dakota</adminName2>
<adminCode3/>
<adminName3/>
</code>
<code>
<postalcode>55087</postalcode>
<name>Warsaw</name>
<countryCode>US</countryCode>
<lat>44.24854</lat>
<lng>-93.39488</lng>
<adminCode1>MN</adminCode1>
<adminName1>Minnesota</adminName1>
<adminCode2>131</adminCode2>
<adminName2>Rice</adminName2>
<adminCode3/>
<adminName3/>
</code>
<code>
<postalcode>55088</postalcode>
<name>Webster</name>
<countryCode>US</countryCode>
<lat>44.50034</lat>
<lng>-93.38257</lng>
<adminCode1>MN</adminCode1>
<adminName1>Minnesota</adminName1>
<adminCode2>131</adminCode2>
<adminName2>Rice</adminName2>
<adminCode3/>
<adminName3/>
</code>
<code>
<postalcode>55089</postalcode>
<name>Welch</name>
<countryCode>US</countryCode>
<lat>44.60301</lat>
<lng>-92.72626</lng>
<adminCode1>MN</adminCode1>
<adminName1>Minnesota</adminName1>
<adminCode2>049</adminCode2>
<adminName2>Goodhue</adminName2>
<adminCode3/>
<adminName3/>
</code>
<code>
<postalcode>55090</postalcode>
<name>Willernie</name>
<countryCode>US</countryCode>
<lat>45.05347</lat>
<lng>-92.95703</lng>
<adminCode1>MN</adminCode1>
<adminName1>Minnesota</adminName1>
<adminCode2>163</adminCode2>
<adminName2>Washington</adminName2>
<adminCode3/>
<adminName3/>
</code>
<code>
<postalcode>55092</postalcode>
<name>Wyoming</name>
<countryCode>US</countryCode>
<lat>45.33642</lat>
<lng>-92.96752</lng>
<adminCode1>MN</adminCode1>
<adminName1>Minnesota</adminName1>
<adminCode2>025</adminCode2>
<adminName2>Chisago</adminName2>
<adminCode3/>
<adminName3/>
</code>
<code>
<postalcode>55101</postalcode>
<name>Saint Paul</name>
<countryCode>US</countryCode>
<lat>44.95117</lat>
<lng>-93.09023</lng>
<adminCode1>MN</adminCode1>
<adminName1>Minnesota</adminName1>
<adminCode2>123</adminCode2>
<adminName2>Ramsey</adminName2>
<adminCode3/>
<adminName3/>
</code>
<code>
<postalcode>55150</postalcode>
<name>Mendota</name>
<countryCode>US</countryCode>
<lat>44.8858</lat>
<lng>-93.16122</lng>
<adminCode1>MN</adminCode1>
<adminName1>Minnesota</adminName1>
<adminCode2>037</adminCode2>
<adminName2>Dakota</adminName2>
<adminCode3/>
<adminName3/>
</code>
<code>
<postalcode>55301</postalcode>
<name>Albertville</name>
<countryCode>US</countryCode>
<lat>45.25342</lat>
<lng>-93.6469</lng>
<adminCode1>MN</adminCode1>
<adminName1>Minnesota</adminName1>
<adminCode2>171</adminCode2>
<adminName2>Wright</adminName2>
<adminCode3/>
<adminName3/>
</code>
<code>
<postalcode>55302</postalcode>
<name>Annandale</name>
<countryCode>US</countryCode>
<lat>45.24827</lat>
<lng>-94.10607</lng>
<adminCode1>MN</adminCode1>
<adminName1>Minnesota</adminName1>
<adminCode2>171</adminCode2>
<adminName2>Wright</adminName2>
<adminCode3/>
<adminName3/>
</code>
<code>
<postalcode>55305</postalcode>
<name>Hopkins</name>
<countryCode>US</countryCode>
<lat>44.95276</lat>
<lng>-93.43723</lng>
<adminCode1>MN</adminCode1>
<adminName1>Minnesota</adminName1>
<adminCode2>053</adminCode2>
<adminName2>Hennepin</adminName2>
<adminCode3/>
<adminName3/>
</code>
<code>
<postalcode>55307</postalcode>
<name>Arlington</name>
<countryCode>US</countryCode>
<lat>44.61528</lat>
<lng>-94.0762</lng>
<adminCode1>MN</adminCode1>
<adminName1>Minnesota</adminName1>
<adminCode2>143</adminCode2>
<adminName2>Sibley</adminName2>
<adminCode3/>
<adminName3/>
</code>
<code>
<postalcode>55308</postalcode>
<name>Becker</name>
<countryCode>US</countryCode>
<lat>45.43654</lat>
<lng>-93.84097</lng>
<adminCode1>MN</adminCode1>
<adminName1>Minnesota</adminName1>
<adminCode2>141</adminCode2>
<adminName2>Sherburne</adminName2>
<adminCode3/>
<adminName3/>
</code>
<code>
<postalcode>55309</postalcode>
<name>Big Lake</name>
<countryCode>US</countryCode>
<lat>45.35065</lat>
<lng>-93.73992</lng>
<adminCode1>MN</adminCode1>
<adminName1>Minnesota</adminName1>
<adminCode2>141</adminCode2>
<adminName2>Sherburne</adminName2>
<adminCode3/>
<adminName3/>
</code>
<code>
<postalcode>55311</postalcode>
<name>Osseo</name>
<countryCode>US</countryCode>
<lat>45.12426</lat>
<lng>-93.49958</lng>
<adminCode1>MN</adminCode1>
<adminName1>Minnesota</adminName1>
<adminCode2>053</adminCode2>
<adminName2>Hennepin</adminName2>
<adminCode3/>
<adminName3/>
</code>
<code>
<postalcode>55312</postalcode>
<name>Brownton</name>
<countryCode>US</countryCode>
<lat>44.72814</lat>
<lng>-94.33061</lng>
<adminCode1>MN</adminCode1>
<adminName1>Minnesota</adminName1>
<adminCode2>085</adminCode2>
<adminName2>McLeod</adminName2>
<adminCode3/>
<adminName3/>
</code>
<code>
<postalcode>55313</postalcode>
<name>Buffalo</name>
<countryCode>US</countryCode>
<lat>45.18137</lat>
<lng>-93.86348</lng>
<adminCode1>MN</adminCode1>
<adminName1>Minnesota</adminName1>
<adminCode2>171</adminCode2>
<adminName2>Wright</adminName2>
<adminCode3/>
<adminName3/>
</code>
<code>
<postalcode>55315</postalcode>
<name>Carver</name>
<countryCode>US</countryCode>
<lat>44.7169</lat>
<lng>-93.68795</lng>
<adminCode1>MN</adminCode1>
<adminName1>Minnesota</adminName1>
<adminCode2>019</adminCode2>
<adminName2>Carver</adminName2>
<adminCode3/>
<adminName3/>
</code>
<code>
<postalcode>55316</postalcode>
<name>Champlin</name>
<countryCode>US</countryCode>
<lat>45.17004</lat>
<lng>-93.38193</lng>
<adminCode1>MN</adminCode1>
<adminName1>Minnesota</adminName1>
<adminCode2>053</adminCode2>
<adminName2>Hennepin</adminName2>
<adminCode3/>
<adminName3/>
</code>
<code>
<postalcode>55317</postalcode>
<name>Chanhassen</name>
<countryCode>US</countryCode>
<lat>44.86792</lat>
<lng>-93.53591</lng>
<adminCode1>MN</adminCode1>
<adminName1>Minnesota</adminName1>
<adminCode2>019</adminCode2>
<adminName2>Carver</adminName2>
<adminCode3/>
<adminName3/>
</code>
<code>
<postalcode>55318</postalcode>
<name>Chaska</name>
<countryCode>US</countryCode>
<lat>44.80607</lat>
<lng>-93.60831</lng>
<adminCode1>MN</adminCode1>
<adminName1>Minnesota</adminName1>
<adminCode2>019</adminCode2>
<adminName2>Carver</adminName2>
<adminCode3/>
<adminName3/>
</code>
<code>
<postalcode>55320</postalcode>
<name>Clearwater</name>
<countryCode>US</countryCode>
<lat>45.38769</lat>
<lng>-94.04525</lng>
<adminCode1>MN</adminCode1>
<adminName1>Minnesota</adminName1>
<adminCode2>171</adminCode2>
<adminName2>Wright</adminName2>
<adminCode3/>
<adminName3/>
</code>
<code>
<postalcode>55321</postalcode>
<name>Cokato</name>
<countryCode>US</countryCode>
<lat>45.07476</lat>
<lng>-94.19105</lng>
<adminCode1>MN</adminCode1>
<adminName1>Minnesota</adminName1>
<adminCode2>171</adminCode2>
<adminName2>Wright</adminName2>
<adminCode3/>
<adminName3/>
</code>
<code>
<postalcode>55322</postalcode>
<name>Cologne</name>
<countryCode>US</countryCode>
<lat>44.76459</lat>
<lng>-93.79825</lng>
<adminCode1>MN</adminCode1>
<adminName1>Minnesota</adminName1>
<adminCode2>019</adminCode2>
<adminName2>Carver</adminName2>
<adminCode3/>
<adminName3/>
</code>
<code>
<postalcode>55324</postalcode>
<name>Darwin</name>
<countryCode>US</countryCode>
<lat>45.10295</lat>
<lng>-94.42493</lng>
<adminCode1>MN</adminCode1>
<adminName1>Minnesota</adminName1>
<adminCode2>093</adminCode2>
<adminName2>Meeker</adminName2>
<adminCode3/>
<adminName3/>
</code>
<code>
<postalcode>55325</postalcode>
<name>Dassel</name>
<countryCode>US</countryCode>
<lat>45.10321</lat>
<lng>-94.33048</lng>
<adminCode1>MN</adminCode1>
<adminName1>Minnesota</adminName1>
<adminCode2>093</adminCode2>
<adminName2>Meeker</adminName2>
<adminCode3/>
<adminName3/>
</code>
<code>
<postalcode>55327</postalcode>
<name>Dayton</name>
<countryCode>US</countryCode>
<lat>45.19816</lat>
<lng>-93.4668</lng>
<adminCode1>MN</adminCode1>
<adminName1>Minnesota</adminName1>
<adminCode2>053</adminCode2>
<adminName2>Hennepin</adminName2>
<adminCode3/>
<adminName3/>
</code>
<code>
<postalcode>55328</postalcode>
<name>Delano</name>
<countryCode>US</countryCode>
<lat>45.03422</lat>
<lng>-93.80164</lng>
<adminCode1>MN</adminCode1>
<adminName1>Minnesota</adminName1>
<adminCode2>171</adminCode2>
<adminName2>Wright</adminName2>
<adminCode3/>
<adminName3/>
</code>
<code>
<postalcode>55331</postalcode>
<name>Excelsior</name>
<countryCode>US</countryCode>
<lat>44.9007</lat>
<lng>-93.57913</lng>
<adminCode1>MN</adminCode1>
<adminName1>Minnesota</adminName1>
<adminCode2>053</adminCode2>
<adminName2>Hennepin</adminName2>
<adminCode3/>
<adminName3/>
</code>
<code>
<postalcode>55332</postalcode>
<name>Fairfax</name>
<countryCode>US</countryCode>
<lat>44.53294</lat>
<lng>-94.72563</lng>
<adminCode1>MN</adminCode1>
<adminName1>Minnesota</adminName1>
<adminCode2>129</adminCode2>
<adminName2>Renville</adminName2>
<adminCode3/>
<adminName3/>
</code>
<code>
<postalcode>55333</postalcode>
<name>Franklin</name>
<countryCode>US</countryCode>
<lat>44.54213</lat>
<lng>-94.89309</lng>
<adminCode1>MN</adminCode1>
<adminName1>Minnesota</adminName1>
<adminCode2>129</adminCode2>
<adminName2>Renville</adminName2>
<adminCode3/>
<adminName3/>
</code>
</geonames>
